telecode/__init__.py
telecode/claude.py
telecode/cli.py
telecode/codex.py
telecode/mcp_server.py
telecode/server.py
telecode/telegram.py
telecode-0.1.6.dist-info/METADATA
telecode-0.1.6.dist-info/WHEEL
telecode-0.1.6.dist-info/entry_points.txt
telecode-0.1.6.dist-info/top_level.txt
telecode-0.1.6.dist-info/RECORD
