Metadata-Version: 2.4
Name: telecode
Version: 0.1.6
Summary: Telegram webhook server that runs Claude Code or Codex in the background
Author: Telecode Contributors
License: MIT
Requires-Python: >=3.10
Requires-Dist: fastapi>=0.110
Requires-Dist: uvicorn>=0.27
Requires-Dist: httpx>=0.27
Requires-Dist: python-dotenv>=1.0
Requires-Dist: ngrok>=0.13.0
Requires-Dist: mcp>=1.25.0
Requires-Dist: fastmcp>=2.0.0
Requires-Dist: websockets<14.0
